{
  "platform": "cls",
  "platform_name": "财联社",
  "data_type": "ACTIVE",
  "total_events": 37,
  "last_updated": "2025-11-21T03:07:41.873905",
  "events": [
    {
      "id": "cls_336857_20251121_2",
      "platform": "cls",
      "title": "中国稀土学会2025学术年会暨稀土新材料与仪器设备展览会定于11月21日至24日在福建省厦门市召开",
      "event_date": "2025-11-21",
      "event_time": "00:00:00",
      "event_datetime": "2025-11-21 00:00:00",
      "category": "事件公告",
      "importance": 5,
      "country": "中国",
      "is_new": false,
      "discovery_date": "2025-11-21",
      "data_status": "ACTIVE",
      "stocks": [],
      "themes": [],
      "concepts": []
    },
    {
      "id": "cls_336860_20251121_2",
      "platform": "cls",
      "title": "2025第二十三届广州国际汽车展览会将于11月21日至30日举办",
      "event_date": "2025-11-21",
      "event_time": "00:00:00",
      "event_datetime": "2025-11-21 00:00:00",
      "category": "事件公告",
      "importance": 5,
      "country": "中国",
      "is_new": false,
      "discovery_date": "2025-11-21",
      "data_status": "ACTIVE",
      "stocks": [],
      "themes": [],
      "concepts": []
    },
    {
      "id": "cls_373364_20251121_2",
      "platform": "cls",
      "title": "第23届广州国际汽车展览会将于11月21日至30日举办",
      "event_date": "2025-11-21",
      "event_time": "00:00:00",
      "event_datetime": "2025-11-21 00:00:00",
      "category": "事件公告",
      "importance": 5,
      "country": "中国",
      "is_new": false,
      "discovery_date": "2025-11-21",
      "data_status": "ACTIVE",
      "stocks": [],
      "themes": [],
      "concepts": []
    },
    {
      "id": "cls_373369_20251121_2",
      "platform": "cls",
      "title": "2025中国5G+工业互联网大会将于11月21日至23日在湖北武汉举办",
      "event_date": "2025-11-21",
      "event_time": "00:00:00",
      "event_datetime": "2025-11-21 00:00:00",
      "category": "事件公告",
      "importance": 5,
      "country": "中国",
      "is_new": false,
      "discovery_date": "2025-11-21",
      "data_status": "ACTIVE",
      "stocks": [],
      "themes": [],
      "concepts": []
    },
    {
      "id": "cls_384173_20251121_2",
      "platform": "cls",
      "title": "2025青岛虚拟现实创新大会将于11月21日至22日举办",
      "event_date": "2025-11-21",
      "event_time": "00:00:00",
      "event_datetime": "2025-11-21 00:00:00",
      "category": "事件公告",
      "importance": 5,
      "country": "中国",
      "is_new": false,
      "discovery_date": "2025-11-21",
      "data_status": "ACTIVE",
      "stocks": [],
      "themes": [],
      "concepts": []
    },
    {
      "id": "cls_388485_20251121_2",
      "platform": "cls",
      "title": "华为将在11月21日发布AI领域的突破性技术，有望解决算力资源利用效率的难题",
      "event_date": "2025-11-21",
      "event_time": "00:00:00",
      "event_datetime": "2025-11-21 00:00:00",
      "category": "事件公告",
      "importance": 5,
      "country": "中国",
      "is_new": true,
      "discovery_date": "2025-11-21",
      "data_status": "ACTIVE",
      "stocks": [],
      "themes": [],
      "concepts": []
    },
    {
      "id": "cls_388489_20251121_2",
      "platform": "cls",
      "title": "国务院总理李强将于11月21日至23日出席在南非约翰内斯堡举行的二十国集团领导人第二十次峰会",
      "event_date": "2025-11-21",
      "event_time": "00:00:00",
      "event_datetime": "2025-11-21 00:00:00",
      "category": "事件公告",
      "importance": 5,
      "country": "中国",
      "is_new": false,
      "discovery_date": "2025-11-21",
      "data_status": "ACTIVE",
      "stocks": [],
      "themes": [],
      "concepts": []
    },
    {
      "id": "cls_388495_20251121_2",
      "platform": "cls",
      "title": "恒指公司：将于11月21日宣布2025年第三季度之恒生指数系列检讨结果",
      "event_date": "2025-11-21",
      "event_time": "00:00:00",
      "event_datetime": "2025-11-21 00:00:00",
      "category": "事件公告",
      "importance": 5,
      "country": "中国香港",
      "is_new": false,
      "discovery_date": "2025-11-21",
      "data_status": "ACTIVE",
      "stocks": [],
      "themes": [],
      "concepts": []
    },
    {
      "id": "cls_388508_20251121_2",
      "platform": "cls",
      "title": "鸿海科技日将于11月21日至22日举办",
      "event_date": "2025-11-21",
      "event_time": "00:00:00",
      "event_datetime": "2025-11-21 00:00:00",
      "category": "事件公告",
      "importance": 5,
      "country": "中国",
      "is_new": false,
      "discovery_date": "2025-11-21",
      "data_status": "ACTIVE",
      "stocks": [],
      "themes": [],
      "concepts": []
    },
    {
      "id": "cls_388534_20251121_2",
      "platform": "cls",
      "title": "博雷顿无驾驶室纯电动矿卡下线仪式暨新车发布会将于11月21日举行",
      "event_date": "2025-11-21",
      "event_time": "00:00:00",
      "event_datetime": "2025-11-21 00:00:00",
      "category": "事件公告",
      "importance": 5,
      "country": "中国",
      "is_new": false,
      "discovery_date": "2025-11-21",
      "data_status": "ACTIVE",
      "stocks": [],
      "themes": [],
      "concepts": []
    },
    {
      "id": "cls_388708_20251121_2",
      "platform": "cls",
      "title": "华为将于11月21日在上海举办2025AI容器应用落地与发展论坛",
      "event_date": "2025-11-21",
      "event_time": "00:00:00",
      "event_datetime": "2025-11-21 00:00:00",
      "category": "事件公告",
      "importance": 5,
      "country": "中国",
      "is_new": true,
      "discovery_date": "2025-11-21",
      "data_status": "ACTIVE",
      "stocks": [],
      "themes": [],
      "concepts": []
    },
    {
      "id": "cls_388479_20251121_2",
      "platform": "cls",
      "title": "今日有2128亿元7天期逆回购到期",
      "event_date": "2025-11-21",
      "event_time": "09:20:00",
      "event_datetime": "2025-11-21 09:20:00",
      "category": "事件公告",
      "importance": 2,
      "country": "中国",
      "is_new": false,
      "discovery_date": "2025-11-21",
      "data_status": "ACTIVE",
      "stocks": [],
      "themes": [],
      "concepts": []
    },
    {
      "id": "cls_388483_20251121_2",
      "platform": "cls",
      "title": "摩尔线程将于11月21日进行网上路演，参加人员为发行人管理层主要成员和保荐人(主承销商)相关人员",
      "event_date": "2025-11-21",
      "event_time": "14:00:00",
      "event_datetime": "2025-11-21 14:00:00",
      "category": "事件公告",
      "importance": 5,
      "country": "中国",
      "is_new": false,
      "discovery_date": "2025-11-21",
      "data_status": "ACTIVE",
      "stocks": [],
      "themes": [],
      "concepts": []
    },
    {
      "id": "cls_373376_20251124_2",
      "platform": "cls",
      "title": "国际指数编制公司MSCI发布11月指数调整结果，所有调整将于11月24日收盘后实施",
      "event_date": "2025-11-24",
      "event_time": "00:00:00",
      "event_datetime": "2025-11-24 00:00:00",
      "category": "事件公告",
      "importance": 5,
      "country": "中国",
      "is_new": false,
      "discovery_date": "2025-11-21",
      "data_status": "ACTIVE",
      "stocks": [],
      "themes": [],
      "concepts": []
    },
    {
      "id": "cls_373379_20251124_2",
      "platform": "cls",
      "title": "中国汽车工业协会：2025中国汽车供应链大会于11月24日至26日召开",
      "event_date": "2025-11-24",
      "event_time": "00:00:00",
      "event_datetime": "2025-11-24 00:00:00",
      "category": "事件公告",
      "importance": 5,
      "country": "中国",
      "is_new": false,
      "discovery_date": "2025-11-21",
      "data_status": "ACTIVE",
      "stocks": [],
      "themes": [],
      "concepts": []
    },
    {
      "id": "cls_391081_20251124_2",
      "platform": "cls",
      "title": "2025RISC-V产业发展大会暨RDSA国际论坛将于11月24日至25日在珠海、澳门联动举办",
      "event_date": "2025-11-24",
      "event_time": "00:00:00",
      "event_datetime": "2025-11-24 00:00:00",
      "category": "事件公告",
      "importance": 5,
      "country": "中国",
      "is_new": true,
      "discovery_date": "2025-11-21",
      "data_status": "ACTIVE",
      "stocks": [],
      "themes": [],
      "concepts": []
    },
    {
      "id": "cls_391103_20251124_2",
      "platform": "cls",
      "title": "2025全球BC技术创新峰会将于11月24日至25日举办",
      "event_date": "2025-11-24",
      "event_time": "00:00:00",
      "event_datetime": "2025-11-24 00:00:00",
      "category": "事件公告",
      "importance": 5,
      "country": "中国",
      "is_new": true,
      "discovery_date": "2025-11-21",
      "data_status": "ACTIVE",
      "stocks": [],
      "themes": [],
      "concepts": []
    },
    {
      "id": "cls_391106_20251124_2",
      "platform": "cls",
      "title": "2025年第二届中国国际锂业大会将于11月24日至26日在四川举办",
      "event_date": "2025-11-24",
      "event_time": "00:00:00",
      "event_datetime": "2025-11-24 00:00:00",
      "category": "事件公告",
      "importance": 5,
      "country": "中国",
      "is_new": true,
      "discovery_date": "2025-11-21",
      "data_status": "ACTIVE",
      "stocks": [],
      "themes": [],
      "concepts": []
    },
    {
      "id": "cls_383274_20251124_2",
      "platform": "cls",
      "title": "今日有2830亿元7天期逆回购到期",
      "event_date": "2025-11-24",
      "event_time": "17:20:00",
      "event_datetime": "2025-11-24 17:20:00",
      "category": "事件公告",
      "importance": 2,
      "country": "中国",
      "is_new": true,
      "discovery_date": "2025-11-21",
      "data_status": "ACTIVE",
      "stocks": [],
      "themes": [],
      "concepts": []
    },
    {
      "id": "cls_336854_20251125_2",
      "platform": "cls",
      "title": "国际铜业协会日中国论坛将于11月25日在上海举行",
      "event_date": "2025-11-25",
      "event_time": "00:00:00",
      "event_datetime": "2025-11-25 00:00:00",
      "category": "事件公告",
      "importance": 5,
      "country": "中国",
      "is_new": false,
      "discovery_date": "2025-11-21",
      "data_status": "ACTIVE",
      "stocks": [],
      "themes": [],
      "concepts": []
    },
    {
      "id": "cls_382284_20251125_2",
      "platform": "cls",
      "title": "华为Mate 80系列将于11月25日发布",
      "event_date": "2025-11-25",
      "event_time": "00:00:00",
      "event_datetime": "2025-11-25 00:00:00",
      "category": "事件公告",
      "importance": 5,
      "country": "中国",
      "is_new": false,
      "discovery_date": "2025-11-21",
      "data_status": "ACTIVE",
      "stocks": [],
      "themes": [],
      "concepts": []
    },
    {
      "id": "cls_336979_20251127_2",
      "platform": "cls",
      "title": "亚洲通用航空展将于11月27日至30日在珠海举行",
      "event_date": "2025-11-27",
      "event_time": "00:00:00",
      "event_datetime": "2025-11-27 00:00:00",
      "category": "事件公告",
      "importance": 5,
      "country": "中国",
      "is_new": false,
      "discovery_date": "2025-11-21",
      "data_status": "ACTIVE",
      "stocks": [],
      "themes": [],
      "concepts": []
    },
    {
      "id": "cls_333570_20251127_2",
      "platform": "cls",
      "title": "美联储公布经济状况褐皮书",
      "event_date": "2025-11-27",
      "event_time": "11:00:00",
      "event_datetime": "2025-11-27 11:00:00",
      "category": "事件公告",
      "importance": 3,
      "country": "美国",
      "is_new": false,
      "discovery_date": "2025-11-21",
      "data_status": "ACTIVE",
      "stocks": [],
      "themes": [],
      "concepts": []
    },
    {
      "id": "cls_328148_20251128_2",
      "platform": "cls",
      "title": "2025第三届新质生产力汽车大会将于11月28日至30日召开",
      "event_date": "2025-11-28",
      "event_time": "00:00:00",
      "event_datetime": "2025-11-28 00:00:00",
      "category": "事件公告",
      "importance": 5,
      "country": "中国",
      "is_new": false,
      "discovery_date": "2025-11-21",
      "data_status": "ACTIVE",
      "stocks": [],
      "themes": [],
      "concepts": []
    },
    {
      "id": "cls_328149_20251128_2",
      "platform": "cls",
      "title": "2025软件技术大会将于11月28日在北京举行",
      "event_date": "2025-11-28",
      "event_time": "00:00:00",
      "event_datetime": "2025-11-28 00:00:00",
      "category": "事件公告",
      "importance": 5,
      "country": "中国",
      "is_new": false,
      "discovery_date": "2025-11-21",
      "data_status": "ACTIVE",
      "stocks": [],
      "themes": [],
      "concepts": []
    },
    {
      "id": "cls_336833_20251128_2",
      "platform": "cls",
      "title": "鸿蒙星光盛典将于11月28日在深圳举行",
      "event_date": "2025-11-28",
      "event_time": "00:00:00",
      "event_datetime": "2025-11-28 00:00:00",
      "category": "事件公告",
      "importance": 5,
      "country": "中国",
      "is_new": false,
      "discovery_date": "2025-11-21",
      "data_status": "ACTIVE",
      "stocks": [],
      "themes": [],
      "concepts": []
    },
    {
      "id": "cls_336838_20251128_2",
      "platform": "cls",
      "title": "恒生生物科技指数期货将于11月28日开始交易",
      "event_date": "2025-11-28",
      "event_time": "00:00:00",
      "event_datetime": "2025-11-28 00:00:00",
      "category": "事件公告",
      "importance": 5,
      "country": "中国",
      "is_new": false,
      "discovery_date": "2025-11-21",
      "data_status": "ACTIVE",
      "stocks": [],
      "themes": [],
      "concepts": []
    },
    {
      "id": "cls_371647_20251208_2",
      "platform": "cls",
      "title": "证监会公布《证券结算风险基金管理办法》，自2025年12月8日起施行",
      "event_date": "2025-12-08",
      "event_time": "00:00:00",
      "event_datetime": "2025-12-08 00:00:00",
      "category": "事件公告",
      "importance": 5,
      "country": "中国",
      "is_new": false,
      "discovery_date": "2025-11-21",
      "data_status": "ACTIVE",
      "stocks": [],
      "themes": [],
      "concepts": []
    },
    {
      "id": "cls_360984_20251208_2",
      "platform": "cls",
      "title": "国内成品油将开启新一轮调价窗口",
      "event_date": "2025-12-08",
      "event_time": "08:00:00",
      "event_datetime": "2025-12-08 08:00:00",
      "category": "事件公告",
      "importance": 3,
      "country": "中国",
      "is_new": false,
      "discovery_date": "2025-11-21",
      "data_status": "ACTIVE",
      "stocks": [],
      "themes": [],
      "concepts": []
    },
    {
      "id": "cls_371638_20251210_2",
      "platform": "cls",
      "title": "2025中国铂族金属市场年会定于12月10日在三亚召开",
      "event_date": "2025-12-10",
      "event_time": "00:00:00",
      "event_datetime": "2025-12-10 00:00:00",
      "category": "事件公告",
      "importance": 5,
      "country": "中国",
      "is_new": false,
      "discovery_date": "2025-11-21",
      "data_status": "ACTIVE",
      "stocks": [],
      "themes": [],
      "concepts": []
    },
    {
      "id": "cls_366026_20251210_2",
      "platform": "cls",
      "title": "EIA公布月度短期能源展望报告",
      "event_date": "2025-12-10",
      "event_time": "09:00:00",
      "event_datetime": "2025-12-10 09:00:00",
      "category": "事件公告",
      "importance": 3,
      "country": "美国",
      "is_new": false,
      "discovery_date": "2025-11-21",
      "data_status": "ACTIVE",
      "stocks": [],
      "themes": [],
      "concepts": []
    },
    {
      "id": "cls_371641_20251215_2",
      "platform": "cls",
      "title": "2025中国汽车软件大会将于12月15日至16日在上海嘉定召开",
      "event_date": "2025-12-15",
      "event_time": "00:00:00",
      "event_datetime": "2025-12-15 00:00:00",
      "category": "事件公告",
      "importance": 5,
      "country": "中国",
      "is_new": false,
      "discovery_date": "2025-11-21",
      "data_status": "ACTIVE",
      "stocks": [],
      "themes": [],
      "concepts": []
    },
    {
      "id": "cls_388557_20251217_2",
      "platform": "cls",
      "title": "2025小米人车家全生态合作伙伴大会将于12月17日举办",
      "event_date": "2025-12-17",
      "event_time": "00:00:00",
      "event_datetime": "2025-12-17 00:00:00",
      "category": "事件公告",
      "importance": 5,
      "country": "中国",
      "is_new": false,
      "discovery_date": "2025-11-21",
      "data_status": "ACTIVE",
      "stocks": [],
      "themes": [],
      "concepts": []
    },
    {
      "id": "cls_371649_20251218_2",
      "platform": "cls",
      "title": "12月18日，海南自由贸易港正式启动全岛封关运作",
      "event_date": "2025-12-18",
      "event_time": "00:00:00",
      "event_datetime": "2025-12-18 00:00:00",
      "category": "事件公告",
      "importance": 5,
      "country": "中国",
      "is_new": false,
      "discovery_date": "2025-11-21",
      "data_status": "ACTIVE",
      "stocks": [],
      "themes": [],
      "concepts": []
    },
    {
      "id": "cls_371643_20251219_2",
      "platform": "cls",
      "title": "2025进博优品交易会将于12月19日至21日在上海举办",
      "event_date": "2025-12-19",
      "event_time": "00:00:00",
      "event_datetime": "2025-12-19 00:00:00",
      "category": "事件公告",
      "importance": 5,
      "country": "中国",
      "is_new": false,
      "discovery_date": "2025-11-21",
      "data_status": "ACTIVE",
      "stocks": [],
      "themes": [],
      "concepts": []
    },
    {
      "id": "cls_388559_20251219_2",
      "platform": "cls",
      "title": "摩尔线程MUSA开发者大会定档12月19日，将发布全新产品和架构",
      "event_date": "2025-12-19",
      "event_time": "00:00:00",
      "event_datetime": "2025-12-19 00:00:00",
      "category": "事件公告",
      "importance": 5,
      "country": "中国",
      "is_new": false,
      "discovery_date": "2025-11-21",
      "data_status": "ACTIVE",
      "stocks": [],
      "themes": [],
      "concepts": []
    },
    {
      "id": "cls_271503_20260120_2",
      "platform": "cls",
      "title": "首届北京中关村学院青年论坛将于2月20日至21日举办",
      "event_date": "2026-01-20",
      "event_time": "00:00:00",
      "event_datetime": "2026-01-20 00:00:00",
      "category": "事件公告",
      "importance": 5,
      "country": "中国",
      "is_new": true,
      "discovery_date": "2025-11-21",
      "data_status": "ACTIVE",
      "stocks": [],
      "themes": [],
      "concepts": []
    }
  ]
}