{
  "platform": "jiuyangongshe",
  "platform_name": "韭研公社",
  "data_type": "ACTIVE",
  "total_events": 32,
  "last_updated": "2025-11-23T03:24:00.655984",
  "events": [
    {
      "id": "jygs_75d52e34fdc54adb8f688abd7c2bbb23_d44d1373ac3a4869933626541c0c55bf_20251123",
      "platform": "jiuyangongshe",
      "title": "中国国际半导体博览会",
      "event_date": "2025-11-23",
      "content": "",
      "importance": 1,
      "country": "中国",
      "is_new": false,
      "discovery_date": "2025-11-23",
      "data_status": "ACTIVE",
      "stocks": [],
      "themes": [],
      "concepts": []
    },
    {
      "id": "jygs_8ec53df771284dec813ab8fcad401cf3_52eb537762b84f16980798d608849411_20251123",
      "platform": "jiuyangongshe",
      "title": "第七届世界客商大会",
      "event_date": "2025-11-23",
      "content": "",
      "importance": 1,
      "country": "中国",
      "is_new": false,
      "discovery_date": "2025-11-23",
      "data_status": "ACTIVE",
      "stocks": [],
      "themes": [],
      "concepts": []
    },
    {
      "id": "jygs_b264dfe588304692921b5d7ac9c9b985_654b123340d5443885378667e4bb0e7f_20251124",
      "platform": "jiuyangongshe",
      "title": "2025年华侨华人创业发展洽谈会",
      "event_date": "2025-11-24",
      "content": "",
      "importance": 1,
      "country": "中国",
      "is_new": false,
      "discovery_date": "2025-11-23",
      "data_status": "ACTIVE",
      "stocks": [],
      "themes": [],
      "concepts": []
    },
    {
      "id": "jygs_0737972ac2d14f29814d0522c82a6602_027c32ae4b0f4e428302be54e9489c38_20251125",
      "platform": "jiuyangongshe",
      "title": "2025乐鑫全球开发者大会",
      "event_date": "2025-11-25",
      "content": "",
      "importance": 1,
      "country": "中国",
      "is_new": false,
      "discovery_date": "2025-11-23",
      "data_status": "ACTIVE",
      "stocks": [],
      "themes": [],
      "concepts": []
    },
    {
      "id": "jygs_c1f809e521db46acb6f96ce6a33e2bca_e45e4daf7ceb4a8688a6d65e85580cf5_20251125",
      "platform": "jiuyangongshe",
      "title": "中国国际涂料展",
      "event_date": "2025-11-25",
      "content": "",
      "importance": 1,
      "country": "中国",
      "is_new": false,
      "discovery_date": "2025-11-23",
      "data_status": "ACTIVE",
      "stocks": [],
      "themes": [],
      "concepts": []
    },
    {
      "id": "jygs_a075e7d21d184048b5715b7576f2ce22_1077ee648cc340e2b4e4d8ff2347cde1_20251126",
      "platform": "jiuyangongshe",
      "title": "第二届猫鼬AI消费品行业AI落地嘉年华",
      "event_date": "2025-11-26",
      "content": "",
      "importance": 1,
      "country": "中国",
      "is_new": false,
      "discovery_date": "2025-11-23",
      "data_status": "ACTIVE",
      "stocks": [],
      "themes": [],
      "concepts": []
    },
    {
      "id": "jygs_5707fe3fc00e4ddab4439cf7f6cbab6e_a9ffec4136d34b699a5fb5b52a75edc9_20251127",
      "platform": "jiuyangongshe",
      "title": "世界智能制造大会",
      "event_date": "2025-11-27",
      "content": "",
      "importance": 1,
      "country": "中国",
      "is_new": false,
      "discovery_date": "2025-11-23",
      "data_status": "ACTIVE",
      "stocks": [],
      "themes": [],
      "concepts": []
    },
    {
      "id": "jygs_f1c12759f1074393b376b558ab0dbd3d_98ca55378bef4c68903f977ae8320ac8_20251127",
      "platform": "jiuyangongshe",
      "title": "阿里巴巴首款自研旗舰双显AI眼镜发布",
      "event_date": "2025-11-27",
      "content": "",
      "importance": 1,
      "country": "中国",
      "is_new": false,
      "discovery_date": "2025-11-23",
      "data_status": "ACTIVE",
      "stocks": [],
      "themes": [],
      "concepts": []
    },
    {
      "id": "jygs_bf112fe1743442c181da4e83711ddeaf_658569d7e41f4f2db41da338543a9e2d_20251127",
      "platform": "jiuyangongshe",
      "title": "2025低空装备产业创新发展大会",
      "event_date": "2025-11-27",
      "content": "",
      "importance": 1,
      "country": "中国",
      "is_new": false,
      "discovery_date": "2025-11-23",
      "data_status": "ACTIVE",
      "stocks": [],
      "themes": [],
      "concepts": []
    },
    {
      "id": "jygs_39e3a7a72444420cad16ed8c2dd11e6f_8705c6cdff16452b8db8e4cd1bc737de_20251128",
      "platform": "jiuyangongshe",
      "title": "2025第三届新质生产力汽车大会",
      "event_date": "2025-11-28",
      "content": "",
      "importance": 1,
      "country": "中国",
      "is_new": false,
      "discovery_date": "2025-11-23",
      "data_status": "ACTIVE",
      "stocks": [],
      "themes": [],
      "concepts": []
    },
    {
      "id": "jygs_fda01d9a8d694a3aaf3baf866031ca85_5d49419151a0447db6cc43ccf3dd08d3_20251128",
      "platform": "jiuyangongshe",
      "title": "2025软件技术大会",
      "event_date": "2025-11-28",
      "content": "",
      "importance": 1,
      "country": "中国",
      "is_new": false,
      "discovery_date": "2025-11-23",
      "data_status": "ACTIVE",
      "stocks": [],
      "themes": [],
      "concepts": []
    },
    {
      "id": "jygs_e9789dd8633b47b98916ed8601e2d82c_6ea3c5fd588f4e548c28602eb4115dac_20251129",
      "platform": "jiuyangongshe",
      "title": "2025中国人工智能大会",
      "event_date": "2025-11-29",
      "content": "",
      "importance": 1,
      "country": "中国",
      "is_new": false,
      "discovery_date": "2025-11-23",
      "data_status": "ACTIVE",
      "stocks": [],
      "themes": [],
      "concepts": []
    },
    {
      "id": "jygs_1d709dbbbed04be9a4c1b4e8b82e0f8d_d0592c687f044f7d900a1c20d735491f_20251201",
      "platform": "jiuyangongshe",
      "title": "2025人工智能+产业生态大会",
      "event_date": "2025-12-01",
      "content": "",
      "importance": 1,
      "country": "中国",
      "is_new": false,
      "discovery_date": "2025-11-23",
      "data_status": "ACTIVE",
      "stocks": [],
      "themes": [],
      "concepts": []
    },
    {
      "id": "jygs_24fb52f6c256442aaf91486b928a7e86_edf41806e6314411b2e0b0d6c811b010_20251202",
      "platform": "jiuyangongshe",
      "title": "2025亚洲电视论坛",
      "event_date": "2025-12-02",
      "content": "",
      "importance": 1,
      "country": "中国",
      "is_new": false,
      "discovery_date": "2025-11-23",
      "data_status": "ACTIVE",
      "stocks": [],
      "themes": [],
      "concepts": []
    },
    {
      "id": "jygs_9e3ba47b54d946babfcf7a1b7cc1dfb7_b87222d87a604b0bbc62b21543834369_20251204",
      "platform": "jiuyangongshe",
      "title": "2025机器人应用场景生态大会",
      "event_date": "2025-12-04",
      "content": "",
      "importance": 1,
      "country": "中国",
      "is_new": false,
      "discovery_date": "2025-11-23",
      "data_status": "ACTIVE",
      "stocks": [],
      "themes": [],
      "concepts": []
    },
    {
      "id": "jygs_21072ccc758c4e49a94db59a1eebfc33_0049a5e709684b27aea24f8dcad104b6_20251204",
      "platform": "jiuyangongshe",
      "title": "全球智能机械与电子产品博览会",
      "event_date": "2025-12-04",
      "content": "",
      "importance": 1,
      "country": "中国",
      "is_new": false,
      "discovery_date": "2025-11-23",
      "data_status": "ACTIVE",
      "stocks": [],
      "themes": [],
      "concepts": []
    },
    {
      "id": "jygs_f588ba781c2a44219c49444f879775fa_1d98660463604a86bdfc1c1d916afa53_20251205",
      "platform": "jiuyangongshe",
      "title": "欧洲肿瘤内科学会亚洲年会",
      "event_date": "2025-12-05",
      "content": "",
      "importance": 1,
      "country": "中国",
      "is_new": false,
      "discovery_date": "2025-11-23",
      "data_status": "ACTIVE",
      "stocks": [],
      "themes": [],
      "concepts": []
    },
    {
      "id": "jygs_03f813d62b6f42ee8017d93af06650f5_ee3ef9e214974acf93095098a995105c_20251206",
      "platform": "jiuyangongshe",
      "title": "第67届美国血液学会年会(2025 ASH)",
      "event_date": "2025-12-06",
      "content": "",
      "importance": 1,
      "country": "中国",
      "is_new": false,
      "discovery_date": "2025-11-23",
      "data_status": "ACTIVE",
      "stocks": [],
      "themes": [],
      "concepts": []
    },
    {
      "id": "jygs_b33f1965cdc04b8b8a71f0cf09e62569_e9cacf64f303480ea07bd24cc47c5390_20251207",
      "platform": "jiuyangongshe",
      "title": "新版基本医保药品目录及首版商保创新药目录发布",
      "event_date": "2025-12-07",
      "content": "",
      "importance": 1,
      "country": "中国",
      "is_new": false,
      "discovery_date": "2025-11-23",
      "data_status": "ACTIVE",
      "stocks": [],
      "themes": [],
      "concepts": []
    },
    {
      "id": "jygs_5c9a407113a94b9f85027062ae8907d0_3c2ade2b1a14472d9dc3897671c10fe4_20251208",
      "platform": "jiuyangongshe",
      "title": "第七届联合国环境大会",
      "event_date": "2025-12-08",
      "content": "",
      "importance": 1,
      "country": "中国",
      "is_new": false,
      "discovery_date": "2025-11-23",
      "data_status": "ACTIVE",
      "stocks": [],
      "themes": [],
      "concepts": []
    },
    {
      "id": "jygs_4e7p0r2xq9u_074da51ec1ec456ca5c78efb4f19c5b6_20251209",
      "platform": "jiuyangongshe",
      "title": "Carbontech 2025 金刚石年会（12月9-11日 上海）",
      "event_date": "2025-12-09",
      "content": " 2025金刚石年会以“让更多金刚石应用被看到”为主题，将于12月9-11日在上海新国际博览中心举行，聚焦金刚石在电子功率器件、散热封装、量子传感、精密加工、刀具制造等领域的前沿研究与产业化进展",
      "importance": 1,
      "country": "中国",
      "is_new": false,
      "discovery_date": "2025-11-23",
      "data_status": "ACTIVE",
      "stocks": [],
      "themes": [],
      "concepts": []
    },
    {
      "id": "jygs_394186f7cf8243e6a37f5dc39e4d2e53_98865e3670ee40918d75fb30fb330797_20251209",
      "platform": "jiuyangongshe",
      "title": "Carbontech 2025金刚石年会",
      "event_date": "2025-12-09",
      "content": "",
      "importance": 1,
      "country": "中国",
      "is_new": false,
      "discovery_date": "2025-11-23",
      "data_status": "ACTIVE",
      "stocks": [],
      "themes": [],
      "concepts": []
    },
    {
      "id": "jygs_a7ee8c01bd3f497fa7d423bb2afc4c6a_438e3cbf6fbf4d628da354bd7cdb69fe_20251210",
      "platform": "jiuyangongshe",
      "title": "上海闵行将启幕首个脑机接口未来产业集聚区",
      "event_date": "2025-12-10",
      "content": "",
      "importance": 1,
      "country": "中国",
      "is_new": false,
      "discovery_date": "2025-11-23",
      "data_status": "ACTIVE",
      "stocks": [],
      "themes": [
        "脑机接口"
      ],
      "concepts": []
    },
    {
      "id": "jygs_0f2a11934d994390bdea2c1e4984ad65_0970f1bb98174e8ea8416f6acf25b6c5_20251210",
      "platform": "jiuyangongshe",
      "title": "2025中国铂族金属市场年会",
      "event_date": "2025-12-10",
      "content": "",
      "importance": 1,
      "country": "中国",
      "is_new": false,
      "discovery_date": "2025-11-23",
      "data_status": "ACTIVE",
      "stocks": [],
      "themes": [],
      "concepts": []
    },
    {
      "id": "jygs_8bb3e583873f4c1d9ba88c6eaafa8281_ecde1524f9044a7486d8ec3f773fcd2d_20251210",
      "platform": "jiuyangongshe",
      "title": "ESMO(欧洲肿瘤内科学会)",
      "event_date": "2025-12-10",
      "content": "",
      "importance": 1,
      "country": "中国",
      "is_new": false,
      "discovery_date": "2025-11-23",
      "data_status": "ACTIVE",
      "stocks": [],
      "themes": [],
      "concepts": []
    },
    {
      "id": "jygs_a5ba0ba7a8dc417a9a135cc92e0b9494_18b2d31c8fda44e1a942c70c371a6961_20251212",
      "platform": "jiuyangongshe",
      "title": "2025湖南文化旅游产业博览会",
      "event_date": "2025-12-12",
      "content": "",
      "importance": 1,
      "country": "中国",
      "is_new": false,
      "discovery_date": "2025-11-23",
      "data_status": "ACTIVE",
      "stocks": [],
      "themes": [],
      "concepts": []
    },
    {
      "id": "jygs_262bfb95ce3d45c4b0893a78953b0bce_423ba26942fd49fca02d0bc77fe72d5f_20251215",
      "platform": "jiuyangongshe",
      "title": "2025中国汽车软件大会",
      "event_date": "2025-12-15",
      "content": "",
      "importance": 1,
      "country": "中国",
      "is_new": false,
      "discovery_date": "2025-11-23",
      "data_status": "ACTIVE",
      "stocks": [],
      "themes": [],
      "concepts": []
    },
    {
      "id": "jygs_b59f5140dafd46ba993f7494f54e27b1_2fbaf6171e564ecdb11a52bf99d8268d_20251217",
      "platform": "jiuyangongshe",
      "title": "GDTC 2025全球数据技术大会",
      "event_date": "2025-12-17",
      "content": "",
      "importance": 1,
      "country": "中国",
      "is_new": false,
      "discovery_date": "2025-11-23",
      "data_status": "ACTIVE",
      "stocks": [],
      "themes": [],
      "concepts": []
    },
    {
      "id": "jygs_35394ff671874ff69f7a140d5302cbd4_b859260751664fe9848419869d258584_20251217",
      "platform": "jiuyangongshe",
      "title": "GDTC 2025全球数据技术大会",
      "event_date": "2025-12-17",
      "content": "",
      "importance": 1,
      "country": "中国",
      "is_new": false,
      "discovery_date": "2025-11-23",
      "data_status": "ACTIVE",
      "stocks": [],
      "themes": [],
      "concepts": []
    },
    {
      "id": "jygs_3xrepv06t0t_94fa282e386441f08a8b0ba0a1e682ab_20251218",
      "platform": "jiuyangongshe",
      "title": "海南自由贸易港全岛封关",
      "event_date": "2025-12-18",
      "content": " 2025 年 12 月 18 日正式启动海南自贸港全岛封关运作",
      "importance": 1,
      "country": "中国",
      "is_new": false,
      "discovery_date": "2025-11-23",
      "data_status": "ACTIVE",
      "stocks": [],
      "themes": [],
      "concepts": []
    },
    {
      "id": "jygs_cd214dd5efb24fa0b26e896a2c33123a_2d76a58e4bda4c3f8487da2ecb91ea86_20251219",
      "platform": "jiuyangongshe",
      "title": "首届香港国际AI艺术节",
      "event_date": "2025-12-19",
      "content": "",
      "importance": 1,
      "country": "中国",
      "is_new": false,
      "discovery_date": "2025-11-23",
      "data_status": "ACTIVE",
      "stocks": [],
      "themes": [],
      "concepts": []
    },
    {
      "id": "jygs_47badf532b0340d697a22e11a8a090a4_3b9f6a29dcc64bde93c1cf3e5e8e26d3_20251228",
      "platform": "jiuyangongshe",
      "title": "BCI-2025深圳国际脑机接口创新技术展览会",
      "event_date": "2025-12-28",
      "content": "",
      "importance": 1,
      "country": "中国",
      "is_new": false,
      "discovery_date": "2025-11-23",
      "data_status": "ACTIVE",
      "stocks": [],
      "themes": [
        "脑机接口"
      ],
      "concepts": []
    }
  ]
}